Nuitka_fixed-1.1.2.data/scripts/nuitka-run.bat
Nuitka_fixed-1.1.2.data/scripts/nuitka.bat
nuitka/Builtins.py
nuitka/Bytecodes.py
nuitka/Caching.py
nuitka/Constants.py
nuitka/Errors.py
nuitka/MainControl.py
nuitka/ModuleRegistry.py
nuitka/OptionParsing.py
nuitka/Options.py
nuitka/OutputDirectories.py
nuitka/PostProcessing.py
nuitka/Progress.py
nuitka/PythonFlavors.py
nuitka/PythonOperators.py
nuitka/PythonVersions.py
nuitka/Reports.py
nuitka/SourceCodeReferences.py
nuitka/Tracing.py
nuitka/TreeXML.py
nuitka/Variables.py
nuitka/Version.py
nuitka/__init__.py
nuitka/__main__.py
nuitka/__past__.py
nuitka/build/Backend.scons
nuitka/build/DataComposerInterface.py
nuitka/build/Onefile.scons
nuitka/build/SconsCaching.py
nuitka/build/SconsCompilerSettings.py
nuitka/build/SconsHacks.py
nuitka/build/SconsInterface.py
nuitka/build/SconsProgress.py
nuitka/build/SconsSpawn.py
nuitka/build/SconsUtils.py
nuitka/build/__init__.py
nuitka/build/include/nuitka/allocator.h
nuitka/build/include/nuitka/builtins.h
nuitka/build/include/nuitka/calling.h
nuitka/build/include/nuitka/compiled_asyncgen.h
nuitka/build/include/nuitka/compiled_cell.h
nuitka/build/include/nuitka/compiled_coroutine.h
nuitka/build/include/nuitka/compiled_frame.h
nuitka/build/include/nuitka/compiled_function.h
nuitka/build/include/nuitka/compiled_generator.h
nuitka/build/include/nuitka/compiled_method.h
nuitka/build/include/nuitka/constants_blob.h
nuitka/build/include/nuitka/exceptions.h
nuitka/build/include/nuitka/freelists.h
nuitka/build/include/nuitka/hedley.h
nuitka/build/include/nuitka/helpers.h
nuitka/build/include/nuitka/importing.h
nuitka/build/include/nuitka/incbin.h
nuitka/build/include/nuitka/prelude.h
nuitka/build/include/nuitka/python_pgo.h
nuitka/build/include/nuitka/safe_string_ops.h
nuitka/build/include/nuitka/threading.h
nuitka/build/include/nuitka/tracing.h
nuitka/build/include/nuitka/unfreezing.h
nuitka/build/include/nuitka/helper/attributes.h
nuitka/build/include/nuitka/helper/boolean.h
Nuitka_fixed-1.1.2.dist-info/LICENSE.txt
Nuitka_fixed-1.1.2.dist-info/METADATA
Nuitka_fixed-1.1.2.dist-info/WHEEL
Nuitka_fixed-1.1.2.dist-info/entry_points.txt
Nuitka_fixed-1.1.2.dist-info/top_level.txt
Nuitka_fixed-1.1.2.dist-info/RECORD
